fastapi_handler_exception/__init__.py
fastapi_handler_exception/base.py
fastapi_handler_exception/parsers.py
fastapi_handler_exception/utils.py
fastapi_handler_exception-0.1.1.dist-info/WHEEL
fastapi_handler_exception-0.1.1.dist-info/METADATA
fastapi_handler_exception-0.1.1.dist-info/RECORD
